visionprint/__init__.py
visionprint/ansi.py
visionprint/main.py
visionprint-0.2.4.dist-info/licenses/LICENSE
visionprint-0.2.4.dist-info/METADATA
visionprint-0.2.4.dist-info/WHEEL
visionprint-0.2.4.dist-info/top_level.txt
visionprint-0.2.4.dist-info/RECORD
