Metadata-Version: 2.4
Name: visionprint
Version: 0.2.4
Summary: A small Python utility library offering conditional & expressive styles for CLI output.
Author: melih senlen
License: MIT
Project-URL: github, https://github.com/eard3n1/visionprint
Requires-Python: >=3.8
License-File: LICENSE
Dynamic: license-file
